{
  "updated": "2026-06-21 11:47 UTC",
  "uk": [
    {
      "model": "Apple - MacBook Air 15inch (M4) -10-core CPU/ 10-core GPU -16GB/512GB - Sky B…",
      "retailer": "Joybuy",
      "price": 849,
      "was": null,
      "cat": "Mac",
      "cpu": "Apple M4",
      "ram": "16GB",
      "storage": "512GB",
      "screen": "15\"",
      "gpu": "10-core GPU",
      "battery": "—",
      "weight": "—",
      "img": "https://images.hotukdeals.com/threads/raw/j84Pm/4917222_1/re/320x320/qt/55/4917222_1.jpg",
      "link": "https://www.hotukdeals.com/deals/apple-macbook-air-15inch-m4-10-core-cpu-10-core-gpu-16gb512gb-sky-blue-further-ps5-off-select-accounts-4917222",
      "note": "From Joybuy feed — confirm spec on retailer site"
    },
    {
      "model": "Apple MacBook Air 15 Inch M4 16GB RAM 512GB SSD 2025 - Midnight (10-core GPU)…",
      "retailer": "Costco",
      "price": 839,
      "was": null,
      "cat": "Mac",
      "cpu": "Apple M4",
      "ram": "16GB",
      "storage": "512GB",
      "screen": "15\"",
      "gpu": "10-core GPU",
      "battery": "—",
      "weight": "—",
      "img": "https://images.hotukdeals.com/threads/raw/ZxHkZ/4916700_1/re/320x320/qt/55/4916700_1.jpg",
      "link": "https://www.hotukdeals.com/deals/apple-macbook-air-15-inch-m4-16gb-ram-512gb-ssd-2025-midnight-10-core-gpu-4916700",
      "note": "From Costco feed — confirm spec on retailer site"
    },
    {
      "model": "Apple 2025 MacBook Air 15-inch Laptop, M4 chip 15.3-inch Liquid Retina Displa…",
      "retailer": "Amazon",
      "price": 979,
      "was": null,
      "cat": "Mac",
      "cpu": "Apple M4",
      "ram": "16GB",
      "storage": "512GB",
      "screen": "15\"",
      "gpu": "—",
      "battery": "—",
      "weight": "—",
      "img": "https://images.hotukdeals.com/threads/raw/OJd6x/4916484_1/re/320x320/qt/55/4916484_1.jpg",
      "link": "https://www.hotukdeals.com/deals/apple-2025-macbook-air-15-inch-laptop-with-m4-chip-153-inch-liquid-retina-display-16gb-unified-memory-512gb-ssd-storage-like-new-4916484",
      "note": "From Amazon feed — confirm spec on retailer site"
    },
    {
      "model": "Apple 2025 MacBook Air 15-inch Laptop with M4 chip, 15.3-inch Liquid Retina D…",
      "retailer": "Amazon",
      "price": 979,
      "was": null,
      "cat": "Mac",
      "cpu": "Apple M4",
      "ram": "16GB",
      "storage": "256GB",
      "screen": "15\"",
      "gpu": "—",
      "battery": "—",
      "weight": "—",
      "img": "https://images.hotukdeals.com/threads/raw/ZA3Q2/4916466_1/re/320x320/qt/55/4916466_1.jpg",
      "link": "https://www.hotukdeals.com/deals/apple-2025-macbook-air-15-inch-laptop-with-m4-chip-153-inch-liquid-retina-display-16gb-unified-memory-256gb-ssd-storage-silver-4916466",
      "note": "From Amazon feed — confirm spec on retailer site"
    },
    {
      "model": "ASUS Vivobook V16 16\" Gaming Laptop ( Intel Core 5 210H / RTX5050 8GB / 16GB …",
      "retailer": "Currys",
      "price": 700,
      "was": null,
      "cat": "Gaming",
      "cpu": "Intel Core 5 210H",
      "ram": "8GB",
      "storage": "512GB",
      "screen": "16\"",
      "gpu": "RTX5050",
      "battery": "—",
      "weight": "—",
      "img": "https://images.hotukdeals.com/threads/raw/E7HP3/4916369_1/re/320x320/qt/55/4916369_1.jpg",
      "link": "https://www.hotukdeals.com/deals/asus-vivobook-v16-16-gaming-laptop-intel-core-5-210h-rtx5050-8gb-16gb-ddr5-512gb-144hz-fhd-via-dfc-hs-blc-student-portals-4916369",
      "note": "From Currys feed — confirm spec on retailer site"
    },
    {
      "model": "LENOVO Legion Pro 34WD-10, 34\", OLED, QHD 1440p, 240Hz, KVM",
      "retailer": "Currys",
      "price": 649,
      "was": null,
      "cat": "Gaming",
      "cpu": "—",
      "ram": "—",
      "storage": "—",
      "screen": "34\" OLED QHD 240Hz",
      "gpu": "—",
      "battery": "—",
      "weight": "—",
      "img": "https://images.hotukdeals.com/threads/raw/9LXom/4916235_1/re/320x320/qt/55/4916235_1.jpg",
      "link": "https://www.hotukdeals.com/deals/lenovo-legion-pro-34wd-10-34-oled-qhd-1440p-240hz-kvm-4916235",
      "note": "From Currys feed — confirm spec on retailer site"
    },
    {
      "model": "Samsung Galaxy Book4 Edge 15.6\" Laptop, Copilot+ PC - Snapdragon X Plus, 16GB…",
      "retailer": "Currys",
      "price": 279,
      "was": null,
      "cat": "Windows laptop",
      "cpu": "Snapdragon X Plus",
      "ram": "16GB",
      "storage": "256GB",
      "screen": "15.6\"",
      "gpu": "—",
      "battery": "—",
      "weight": "—",
      "img": "https://images.hotukdeals.com/threads/raw/JaUaJ/4915922_1/re/320x320/qt/55/4915922_1.jpg",
      "link": "https://www.hotukdeals.com/deals/samsung-galaxy-book4-edge-156-laptop-copilot-pc-snapdragon-x-plus-16gb256-gb-ssd-sapphire-blue-wcode-via-hsddfc-free-to-join-4915922",
      "note": "From Currys feed — confirm spec on retailer site"
    },
    {
      "model": "ACER Aspire Go 15 15.6\" Laptop - Intel Core i5 (13420H), 16GB DDR5 (Expandabl…",
      "retailer": "Currys",
      "price": 299,
      "was": null,
      "cat": "Windows laptop",
      "cpu": "Core i5",
      "ram": "16GB",
      "storage": "512GB",
      "screen": "15.6\"",
      "gpu": "—",
      "battery": "—",
      "weight": "—",
      "img": "https://images.hotukdeals.com/threads/raw/h6GjU/4915899_1/re/320x320/qt/55/4915899_1.jpg",
      "link": "https://www.hotukdeals.com/deals/acer-aspire-go-15-156-laptop-intel-core-i5-13420h-16gb-ddr5-expandable-512gb-ssd-wcode-via-hsdstudentbeanstotumblcdftdfc-4915899",
      "note": "From Currys feed — confirm spec on retailer site"
    },
    {
      "model": "APPLE MacBook Air 13.6\" (2025) - M4, 256 GB SSD, Sky Blue",
      "retailer": "Currys",
      "price": 779,
      "was": null,
      "cat": "Mac",
      "cpu": "Apple M4",
      "ram": "—",
      "storage": "256GB",
      "screen": "13.6\"",
      "gpu": "—",
      "battery": "—",
      "weight": "—",
      "img": "https://images.hotukdeals.com/threads/raw/uRXbd/4915856_1/re/320x320/qt/55/4915856_1.jpg",
      "link": "https://www.hotukdeals.com/deals/apple-macbook-air-136-2025-m4-256-gb-ssd-sky-blue-4915856",
      "note": "From Currys feed — confirm spec on retailer site"
    },
    {
      "model": "1TB Biwin M350 PCIe 4.0 M.2 SSD 6000MB/s Desktop & Laptop W/Code @ BNH-UK-SHOP",
      "retailer": "eBay",
      "price": 99,
      "was": null,
      "cat": "Windows laptop",
      "cpu": "—",
      "ram": "—",
      "storage": "1TB",
      "screen": "—",
      "gpu": "—",
      "battery": "—",
      "weight": "—",
      "img": "https://images.hotukdeals.com/threads/raw/Fv94c/4915763_1/re/320x320/qt/55/4915763_1.jpg",
      "link": "https://www.hotukdeals.com/deals/1tb-biwin-m350-pcie-40-m2-ssd-6000mbs-desktop-laptop-4915763",
      "note": "From eBay feed — confirm spec on retailer site"
    },
    {
      "model": "Apple MacBook Pro 2025 14.2in M5 16GB 512GB - Silver - Free C&C",
      "retailer": "Argos",
      "price": 1249,
      "was": null,
      "cat": "Mac",
      "cpu": "Apple M5",
      "ram": "16GB",
      "storage": "512GB",
      "screen": "14.2\"",
      "gpu": "—",
      "battery": "—",
      "weight": "—",
      "img": "https://images.hotukdeals.com/threads/raw/XPyKv/4915758_1/re/320x320/qt/55/4915758_1.jpg",
      "link": "https://www.hotukdeals.com/deals/apple-macbook-pro-2025-142in-m5-16gb-512gb-silver-free-cc-4915758",
      "note": "From Argos feed — confirm spec on retailer site"
    },
    {
      "model": "M5 MacBook Pro 2025 version 16GB RAM 512GB - Instore (Watford)",
      "retailer": "Costco",
      "price": 1200,
      "was": null,
      "cat": "Mac",
      "cpu": "Apple M5",
      "ram": "16GB",
      "storage": "512GB",
      "screen": "—",
      "gpu": "—",
      "battery": "—",
      "weight": "—",
      "img": "https://images.hotukdeals.com/threads/raw/2PC1M/4915717_1/re/320x320/qt/55/4915717_1.jpg",
      "link": "https://www.hotukdeals.com/deals/m5-macbook-pro-2025-version-16gb-ram-512gb-at-costco-watford-instore-4915717",
      "note": "From Costco feed — confirm spec on retailer site"
    },
    {
      "model": "Lenovo Legion go 2 Z2 extreme - With code",
      "retailer": "Very",
      "price": 1170,
      "was": null,
      "cat": "Gaming",
      "cpu": "—",
      "ram": "—",
      "storage": "—",
      "screen": "—",
      "gpu": "—",
      "battery": "—",
      "weight": "—",
      "img": "https://images.hotukdeals.com/threads/raw/M1jXH/4915342_1/re/320x320/qt/55/4915342_1.jpg",
      "link": "https://www.hotukdeals.com/deals/lenovo-legion-go-2-z2-extreme-4915342",
      "note": "From Very feed — confirm spec on retailer site"
    },
    {
      "model": "ACER Aspire 14 AI OLED Laptop - Intel Core Ultra 5 226V, 16GB RAM, 512GB SSD,…",
      "retailer": "Currys",
      "price": 399,
      "was": null,
      "cat": "Premium / ultrabook",
      "cpu": "Core Ultra 5 226V",
      "ram": "16GB",
      "storage": "512GB",
      "screen": "14\" OLED",
      "gpu": "—",
      "battery": "—",
      "weight": "—",
      "img": "https://images.hotukdeals.com/threads/raw/aNoUw/4915256_1/re/320x320/qt/55/4915256_1.jpg",
      "link": "https://www.hotukdeals.com/deals/acer-aspire-14-ai-oled-laptop-intel-core-ultra-5-226v-16gb-ram-512gb-ssd-fhd-oled-400-nits-silver-wcode-via-discountforcarers-4915256",
      "note": "From Currys feed — confirm spec on retailer site"
    },
    {
      "model": "Asus Zenbook 14 - WUXGA, Touch, OLED, Intel Ultra 5 225H, 16GB RAM, 512GB SSD…",
      "retailer": "Very",
      "price": 584,
      "was": null,
      "cat": "Premium / ultrabook",
      "cpu": "Intel Core Ultra 5 225H",
      "ram": "16GB",
      "storage": "512GB",
      "screen": "14\" WUXGA OLED Touch",
      "gpu": "—",
      "battery": "—",
      "weight": "—",
      "img": "https://images.hotukdeals.com/threads/raw/7qubW/4914914_1/re/320x320/qt/55/4914914_1.jpg",
      "link": "https://www.hotukdeals.com/deals/asus-zenbook-14-fhd-touch-oled-intel-ultra-5-225h-16gb-ram-512gb-ssd-win11-laptop-blue-wcode-4914914",
      "note": "From Very feed — confirm spec on retailer site"
    },
    {
      "model": "HP OmniBook 7 AI 14\" - 2K, OLED, Intel Ultra 5 225U, 16GB, 512GB, Laptop / In…",
      "retailer": "Currys",
      "price": 424,
      "was": null,
      "cat": "Premium / ultrabook",
      "cpu": "Intel Core Ultra 5 225U",
      "ram": "16GB",
      "storage": "512GB",
      "screen": "14\" 2K OLED",
      "gpu": "—",
      "battery": "—",
      "weight": "—",
      "img": "https://images.hotukdeals.com/threads/raw/NgVSj/4914350_1/re/320x320/qt/55/4914350_1.jpg",
      "link": "https://www.hotukdeals.com/deals/hp-omnibook-7-ai-14-2k-oled-intel-ultra-5-255u-16gb-512gb-laptop-intel-ultra-7-255u-1tb-ssd-ps509-ps50915-wcode-4914350",
      "note": "From Currys feed — confirm spec on retailer site"
    },
    {
      "model": "ACER Aspire 14 AI - FHD+, OLED, Intel Ultra 5 226V, 16GB RAM, 512GB SSD, Silv…",
      "retailer": "Currys",
      "price": 433,
      "was": null,
      "cat": "Premium / ultrabook",
      "cpu": "Intel Core Ultra 5 226V",
      "ram": "16GB",
      "storage": "512GB",
      "screen": "14\" FHD+ OLED",
      "gpu": "—",
      "battery": "—",
      "weight": "—",
      "img": "https://images.hotukdeals.com/threads/raw/apBdR/4914343_1/re/320x320/qt/55/4914343_1.jpg",
      "link": "https://www.hotukdeals.com/deals/acer-aspire-14-ai-fhd-oled-intel-ultra-5-226v-16gb-ram-512gb-ssd-silver-laptop-with-code-4914343",
      "note": "From Currys feed — confirm spec on retailer site"
    },
    {
      "model": "Apple MacBook Air 2026, Apple M5 Chip, 16GB RAM, 512GB SSD, 13 Inch Sky Blue,…",
      "retailer": "Costco",
      "price": 980,
      "was": null,
      "cat": "Mac",
      "cpu": "Apple M5",
      "ram": "16GB",
      "storage": "512GB",
      "screen": "13\"",
      "gpu": "—",
      "battery": "—",
      "weight": "—",
      "img": "https://images.hotukdeals.com/threads/raw/sAZ7s/4914192_1/re/320x320/qt/55/4914192_1.jpg",
      "link": "https://www.hotukdeals.com/deals/apple-macbook-air-2026-apple-m5-chip-16gb-ram-512gb-ssd-13-inch-sky-blue-starlight-1tb-version-all-colours-ps114998-4914192",
      "note": "From Costco feed — confirm spec on retailer site"
    },
    {
      "model": "Apple MacBook Neo 13-inch Laptop with A18 Pro chip: 8GB Unified Memory, 512GB…",
      "retailer": "Amazon",
      "price": 618,
      "was": null,
      "cat": "Mac",
      "cpu": "Apple A18 Pro",
      "ram": "8GB",
      "storage": "512GB",
      "screen": "13\"",
      "gpu": "—",
      "battery": "—",
      "weight": "—",
      "img": "https://images.hotukdeals.com/threads/raw/7K9UM/4914009_1/re/320x320/qt/55/4914009_1.jpg",
      "link": "https://www.hotukdeals.com/deals/apple-macbook-neo-13-inch-laptop-with-a18-pro-chip-8gb-unified-memory-512gb-ssd-storage-touch-id-silver-prime-members-price-4914009",
      "note": "From Amazon feed — confirm spec on retailer site"
    },
    {
      "model": "Apple MacBook Neo A18, 512GB SSD, Touch ID, 8GB RAM 13-inch Laptop - Silver",
      "retailer": "Amazon",
      "price": 630,
      "was": null,
      "cat": "Mac",
      "cpu": "Apple A18",
      "ram": "8GB",
      "storage": "512GB",
      "screen": "13\"",
      "gpu": "—",
      "battery": "—",
      "weight": "—",
      "img": "https://images.hotukdeals.com/threads/raw/MVRz3/4913184_1/re/320x320/qt/55/4913184_1.jpg",
      "link": "https://www.hotukdeals.com/deals/apple-macbook-neo-13-inch-laptop-512gb-ssd-touch-id-8gb-ram-silver-4913184",
      "note": "From Amazon feed — confirm spec on retailer site"
    }
  ],
  "us": [
    {
      "model": "Dell XPS 13 Core 5 13.4\" Touch Laptop for $600 for students or teachers + fre…",
      "retailer": "Dell",
      "price": 600,
      "was": null,
      "cat": "Windows laptop",
      "cpu": "Intel Core 5",
      "ram": "—",
      "storage": "—",
      "screen": "13.4\" Touch",
      "gpu": "—",
      "battery": "—",
      "weight": "—",
      "img": "https://d.dlnws.com/64599/1781898010-2026-06-19_15-39-24.png?h=240&w=320",
      "link": "https://www.dealnews.com/Dell-XPS-13-Core-5-13-4-Touch-Laptop-for-600-for-students-or-teachers-free-shipping/21843364.html?iref=rss-c49",
      "note": "From Dell feed — confirm spec on retailer site"
    },
    {
      "model": "Dell Laptop Days of Deals: Up to $830 off + free shipping",
      "retailer": "Dell",
      "price": 830,
      "was": null,
      "cat": "Windows laptop",
      "cpu": "—",
      "ram": "—",
      "storage": "—",
      "screen": "—",
      "gpu": "—",
      "battery": "—",
      "weight": "—",
      "img": "https://d.dlnws.com/64599/1781895652-2026-06-19_15-00-33.png?h=240&w=320",
      "link": "https://www.dealnews.com/Dell-Laptop-Days-of-Deals-Up-to-830-off-free-shipping/21843362.html?iref=rss-c49",
      "note": "From Dell feed — confirm spec on retailer site"
    },
    {
      "model": "HP OMEN Ryzen AI 7 17.3\" RTX 5070 Gaming Laptop for $1,500 + free shipping",
      "retailer": "HP",
      "price": 1500,
      "was": null,
      "cat": "Gaming",
      "cpu": "Ryzen AI 7 17",
      "ram": "—",
      "storage": "—",
      "screen": "17.3\"",
      "gpu": "RTX 5070",
      "battery": "—",
      "weight": "—",
      "img": "https://d.dlnws.com/64599/1781891437-24c1_omen_avid_17_shadow-black_nt_1-zone_hdcam_nonfpr_hfr_coreset_front_4126115.webp?h=240&w=320",
      "link": "https://www.dealnews.com/HP-OMEN-Ryzen-AI-7-17-3-RTX-5070-Gaming-Laptop-for-1-500-free-shipping/21843345.html?iref=rss-c49",
      "note": "From HP feed — confirm spec on retailer site"
    },
    {
      "model": "Lenovo IdeaPad Slim 3i 13th-Gen. i5 15.6\" Laptop for $470 + free shipping",
      "retailer": "Lenovo",
      "price": 470,
      "was": null,
      "cat": "Windows laptop",
      "cpu": "Intel Core i5 (13th Gen)",
      "ram": "—",
      "storage": "—",
      "screen": "15.6\"",
      "gpu": "—",
      "battery": "—",
      "weight": "—",
      "img": "https://d.dlnws.com/64599/1781813119-c6199c31-992f-4363-9c38-15ad8f286c93-jpg-maxheight-1920-maxwidth-900.webp?h=240&w=320",
      "link": "https://www.dealnews.com/Lenovo-Idea-Pad-Slim-3-i-13-th-Gen-i5-15-6-Laptop-for-470-free-shipping/21842428.html?iref=rss-c49",
      "note": "From Lenovo feed — confirm spec on retailer site"
    },
    {
      "model": "Dell 14 Plus Ultra 7 258V 14\" Laptop w/ 32GB RAM & 1TB SSD for $940 + free sh…",
      "retailer": "Dell",
      "price": 940,
      "was": null,
      "cat": "Windows laptop",
      "cpu": "Intel Core Ultra 7 258V",
      "ram": "32GB",
      "storage": "1TB",
      "screen": "14\"",
      "gpu": "—",
      "battery": "—",
      "weight": "—",
      "img": "https://d.dlnws.com/64599/1781811575-laptop-dell-db14250-copilot-pc-mg-png.avif?h=240&w=320",
      "link": "https://www.dealnews.com/Dell-14-Plus-Ultra-7-258-V-14-Laptop-w-32-GB-RAM-1-TB-SSD-for-940-free-shipping/21842419.html?iref=rss-c49",
      "note": "From Dell feed — confirm spec on retailer site"
    },
    {
      "model": "Dell 16 Ryzen 7 250 16\" Touchscreen Laptop for $550 + free shipping",
      "retailer": "Dell",
      "price": 550,
      "was": null,
      "cat": "Windows laptop",
      "cpu": "Ryzen 7 250",
      "ram": "—",
      "storage": "—",
      "screen": "16\" Touchscreen",
      "gpu": "—",
      "battery": "—",
      "weight": "—",
      "img": "https://d.dlnws.com/64599/1781809616-notebook-dc16255-nt-black-gallery-1-psd.avif?h=240&w=320",
      "link": "https://www.dealnews.com/Dell-16-Ryzen-7-250-16-Touchscreen-Laptop-for-550-free-shipping/21842412.html?iref=rss-c49",
      "note": "From Dell feed — confirm spec on retailer site"
    },
    {
      "model": "Dell 15 13th-Gen i5 15.6\" Laptop w/ 16GB RAM & 512GB SSD for $450 + free ship…",
      "retailer": "Dell",
      "price": 450,
      "was": null,
      "cat": "Windows laptop",
      "cpu": "Intel Core i5 (13th Gen)",
      "ram": "16GB",
      "storage": "512GB",
      "screen": "15.6\"",
      "gpu": "—",
      "battery": "—",
      "weight": "—",
      "img": "https://d.dlnws.com/64599/1781540939-laptop-dell-dc15250nt-bk-plastic-gallery-1-psd.avif?h=240&w=320",
      "link": "https://www.dealnews.com/Dell-15-13-th-Gen-i5-15-6-Laptop-w-16-GB-RAM-512-GB-SSD-for-450-free-shipping/21842411.html?iref=rss-c49",
      "note": "From Dell feed — confirm spec on retailer site"
    },
    {
      "model": "Dell XPS 13 DX13260 13.4\" Laptop for $700 w/ $50 Dell Credit + free shipping",
      "retailer": "Dell",
      "price": 700,
      "was": null,
      "cat": "Windows laptop",
      "cpu": "—",
      "ram": "—",
      "storage": "—",
      "screen": "13.4\"",
      "gpu": "—",
      "battery": "—",
      "weight": "—",
      "img": "https://d.dlnws.com/64599/1781708254-laptop-xps-13-sky-dx13260-silver-gallery-1.avif?h=240&w=320",
      "link": "https://www.dealnews.com/Dell-XPS-13-DX13260-13-4-Laptop-for-700-w-50-Dell-Credit-free-shipping/21841376.html?iref=rss-c49",
      "note": "From Dell feed — confirm spec on retailer site"
    },
    {
      "model": "Alienware 16x Core Ultra 9 16\" Gaming Laptop w/ NVIDIA GeForce RTX 5070, 32GB…",
      "retailer": "dealnews",
      "price": 2100,
      "was": null,
      "cat": "Gaming",
      "cpu": "Core Ultra 9 16",
      "ram": "32GB",
      "storage": "1TB",
      "screen": "16\"",
      "gpu": "RTX 5070",
      "battery": "—",
      "weight": "—",
      "img": "https://d.dlnws.com/64599/1781104103-laptop-alienware-ac16251-blue-ff-gallery-1-psd.avif?h=240&w=320",
      "link": "https://www.dealnews.com/Alienware-16-x-Core-Ultra-9-16-Gaming-Laptop-w-NVIDIA-Ge-Force-RTX-5070-32-GB-1-TB-for-2-100-free-shipping/21841128.html?iref=rss-c49",
      "note": "From dealnews feed — confirm spec on retailer site"
    },
    {
      "model": "Mallrace 15.6\" Windows 11 with Intel i5 Processor 16GB RAM 512GB SSD Laptop f…",
      "retailer": "dealnews",
      "price": 465,
      "was": null,
      "cat": "Windows laptop",
      "cpu": "Intel Core i5",
      "ram": "16GB",
      "storage": "512GB",
      "screen": "15.6\"",
      "gpu": "—",
      "battery": "—",
      "weight": "—",
      "img": "https://d.dlnws.com/64599/1781624166-draftworks_img_grt1u8i1lopqcfpldcl.jpeg?h=240&w=320",
      "link": "https://www.dealnews.com/Mallrace-15-6-Windows-11-with-Intel-i5-Processor-16-GB-RAM-512-GB-SSD-Laptop-for-465-free-shipping/21841072.html?iref=rss-c49",
      "note": "From dealnews feed — confirm spec on retailer site"
    },
    {
      "model": "HP Omnibook 5 16\" Core 5 120U Laptop for $580 + free shipping",
      "retailer": "HP",
      "price": 580,
      "was": null,
      "cat": "Windows laptop",
      "cpu": "Intel Core 5 120U",
      "ram": "—",
      "storage": "—",
      "screen": "16\"",
      "gpu": "—",
      "battery": "—",
      "weight": "—",
      "img": "https://d.dlnws.com/64599/1781548167-25c1_omnibook-5_16_glacier-silver_nt_hd-cam_nonfpr_backlit_nonoled_nonai_copilot_win11_core-set_front_3777701.jpg?h=240&w=320",
      "link": "https://www.dealnews.com/HP-Omnibook-5-16-Core-5-120-U-Laptop-for-580-free-shipping/21840804.html?iref=rss-c49",
      "note": "From HP feed — confirm spec on retailer site"
    },
    {
      "model": "HP Core Ultra 5 225U 15.6\" Laptop for $460 + free shipping",
      "retailer": "HP",
      "price": 460,
      "was": null,
      "cat": "Windows laptop",
      "cpu": "Core Ultra 5 225U",
      "ram": "—",
      "storage": "—",
      "screen": "15.6\"",
      "gpu": "—",
      "battery": "—",
      "weight": "—",
      "img": "https://d.dlnws.com/64599/1781547312-23c1_intel_opp_sebastian_15_df_jetblack_nt_hdcam_nonfpr_nonodd_nonbacklit_featherscreen_coreset_front_whitebg_4738588.webp?h=240&w=320",
      "link": "https://www.dealnews.com/HP-Core-Ultra-5-225-U-15-6-Laptop-for-460-free-shipping/21840801.html?iref=rss-c49",
      "note": "From HP feed — confirm spec on retailer site"
    },
    {
      "model": "Dell 16 Plus Core Ultra 5 226V 16\" Laptop w/ 16GB RAM for $800 + free shipping",
      "retailer": "Dell",
      "price": 800,
      "was": null,
      "cat": "Windows laptop",
      "cpu": "Core Ultra 5 226V",
      "ram": "16GB",
      "storage": "—",
      "screen": "16\"",
      "gpu": "—",
      "battery": "—",
      "weight": "—",
      "img": "https://d.dlnws.com/64599/1768990969-microsoft-surface-laptop-front-view-zyge.png?h=240&w=320",
      "link": "https://www.dealnews.com/products/Dell/Dell-16-Plus-Core-Ultra-5-226-V-16-Laptop-w-16-GB-RAM/497372.html?iref=rss-c49",
      "note": "From Dell feed — confirm spec on retailer site"
    },
    {
      "model": "Dell 15 Core 3 100U 15.6\" Laptop for $350 + free shipping",
      "retailer": "Dell",
      "price": 350,
      "was": null,
      "cat": "Windows laptop",
      "cpu": "Intel Core 3 100U",
      "ram": "—",
      "storage": "—",
      "screen": "15.6\"",
      "gpu": "—",
      "battery": "—",
      "weight": "—",
      "img": "https://d.dlnws.com/64599/1781540939-laptop-dell-dc15250nt-bk-plastic-gallery-1-psd.avif?h=240&w=320",
      "link": "https://www.dealnews.com/Dell-15-Core-3-100-U-15-6-Laptop-for-350-free-shipping/21840779.html?iref=rss-c49",
      "note": "From Dell feed — confirm spec on retailer site"
    },
    {
      "model": "Newegg Laptop Clearance at eBay: Up to 55% off + free shipping",
      "retailer": "Newegg",
      "price": null,
      "was": null,
      "cat": "Windows laptop",
      "cpu": "—",
      "ram": "—",
      "storage": "—",
      "screen": "—",
      "gpu": "—",
      "battery": "—",
      "weight": "—",
      "img": "https://d.dlnws.com/64599/1781363746-product-trimmed.jpg?h=240&w=320",
      "link": "https://www.dealnews.com/Newegg-Laptop-Clearance-at-eBay-Up-to-55-off-free-shipping/21842272.html?iref=rss-c49",
      "note": "From Newegg feed — confirm spec on retailer site"
    },
    {
      "model": "Lenovo Laptop Deals : Up to 46% off + free shipping",
      "retailer": "Lenovo",
      "price": null,
      "was": null,
      "cat": "Windows laptop",
      "cpu": "—",
      "ram": "—",
      "storage": "—",
      "screen": "—",
      "gpu": "—",
      "battery": "—",
      "weight": "—",
      "img": "https://d.dlnws.com/64599/1781545341-27191865862_thinkbook14gen7arpcosmicblue_202504150324381765818015383-png.avif?h=240&w=320",
      "link": "https://www.dealnews.com/Lenovo-Laptop-Deals-Up-to-46-off-free-shipping/21840796.html?iref=rss-c49",
      "note": "From Lenovo feed — confirm spec on retailer site"
    }
  ]
}